kognic/base_clients/__init__.py
kognic/base_clients/_version.py
kognic/base_clients/async_retry_support.py
kognic/base_clients/http_client.py
kognic/base_clients/models.py
kognic/base_clients/retry_support.py
kognic/base_clients/util.py
kognic/base_clients/cloud_storage/__init__.py
kognic/base_clients/cloud_storage/async_file_resource_client.py
kognic/base_clients/cloud_storage/download_handler.py
kognic/base_clients/cloud_storage/file_resource_client.py
kognic/base_clients/cloud_storage/network_limits.py
kognic/base_clients/cloud_storage/upload_handler.py
kognic/base_clients/cloud_storage/upload_spec.py
kognic_base_clients-2.4.0.dist-info/METADATA
kognic_base_clients-2.4.0.dist-info/WHEEL
kognic_base_clients-2.4.0.dist-info/top_level.txt
kognic_base_clients-2.4.0.dist-info/RECORD
