Metadata-Version: 2.4
Name: kognic-base-clients
Version: 2.4.0
Summary: Kognic Base Clients
Author-email: Kognic <scenes-and-predictions@kognic.com>
License: MIT
Project-URL: homepage, https://github.com/annotell/kognic-base-clients-python
Keywords: Kognic,API
Classifier: Development Status :: 5 - Production/Stable
Classifier: License :: OSI Approved :: MIT License
Classifier: Intended Audience :: Developers
Classifier: Programming Language :: Python :: 3
Requires-Python: >=3.9
Requires-Dist: kognic-auth<4,>=3.0.0
Requires-Dist: requests<3,>=2.23.0
Requires-Dist: pydantic<3,>=2
Requires-Dist: httpx<1,>=0.20
